app/__init__.py
app/main.py
shared/__init__.py
shared/api.py
shared/client_manager.py
shared/error_handler.py
shared/types.py
xhs/__init__.py
xhs/api.py
xhs/exception.py
xhs/help.py
iflow_mcp_xhs_mcp_agent-0.1.0.dist-info/METADATA
iflow_mcp_xhs_mcp_agent-0.1.0.dist-info/WHEEL
iflow_mcp_xhs_mcp_agent-0.1.0.dist-info/entry_points.txt
iflow_mcp_xhs_mcp_agent-0.1.0.dist-info/top_level.txt
iflow_mcp_xhs_mcp_agent-0.1.0.dist-info/RECORD
