Metadata-Version: 2.4
Name: iflow-mcp_xhs-mcp-agent
Version: 0.1.0
Summary: Xiaohongshu API MCP Server
Requires-Python: >=3.10
Requires-Dist: fastapi>=0.115.12
Requires-Dist: uvicorn>=0.34.2
Requires-Dist: pydantic>=2.4.2
Requires-Dist: requests>=2.31.0
Requires-Dist: lxml>=4.9.3
Requires-Dist: mcp>=1.0.0
Requires-Dist: httpx>=0.27.0
Requires-Dist: aiohttp>=3.9.0
